fastanalyzer/__init__.py
fastanalyzer/data_calc.py
fastanalyzer/fastanalyzer.py
fastanalyzer/plot.py
fastanalyzer/plot_settings.py
fastanalyzer/rc_ressources.py
fastanalyzer/ui_data_calc.py
fastanalyzer/ui_fastanalyzer.py
fastanalyzer/ui_plot.py
fastanalyzer/ui_plot_settings.py
fastanalyzer-0.1.2.dist-info/LICENSE
fastanalyzer-0.1.2.dist-info/METADATA
fastanalyzer-0.1.2.dist-info/WHEEL
fastanalyzer-0.1.2.dist-info/entry_points.txt
fastanalyzer-0.1.2.dist-info/top_level.txt
fastanalyzer-0.1.2.dist-info/RECORD
